Workbook

Sheet Summary
A1: Value number — support hire avoided (CFO worksheet)
A2: Blue = input with source · green = link to another tab · black = formula. Every calculated cell recomputes from 'Tickets (raw)' and 'Sources'. Type: cost AVOIDANCE (req not opened), not a cut to existing spend.
A4: Inputs
A5: Claimed support load (h/week) | B5: =Sources!$D$5 -> 40 | C5: slack_export.md L176 (Liam, Ops): 'easily 40 hrs/week'
A6: FTE requested | B6: =Sources!$D$6 -> 1 | C6: slack_export.md L188: 'a full-time person's worth, minimum'
A7: Weeks per quarter | B7: 13 | C7: Finance convention (52 / 4). Data span is 12.7 weeks; using 13 is slightly conservative.
A8: Hours per FTE per week | B8: 40 | C8: Full-time week.
A9: Loaded personnel cost, Q1 | B9: =Sources!$D$3 -> 3120000 | C9: pnl_q1_2026.csv L7 — 'Salaries & benefits (all teams)', note: '~300 FTE; loaded cost'
A10: Headcount (FTE) | B10: =Sources!$D$4 -> 300 | C10: headcount_roster.csv L18 — TOTAL,300
A11: Incremental FTE actually needed | B11: 0 | C11: Judgment: current team already absorbs the load (138 of 140 Q1 tickets closed). Stress-tested on 'Stress tests'.
A13: Measured load (from all ticket rows)
A14: Tickets, Q1 2026 | B14: =COUNTA('Tickets (raw)'!$B$3:$B$142) -> 140 | C14: support_tickets_q1_2026.csv L2–L141
A15: Handle minutes, Q1 | B15: =SUM('Tickets (raw)'!$G$3:$G$142) -> 4230 | C15: Sum of Handle_Minutes, every row
A16: Hours per quarter | B16: =B15/60 -> 70.5
A17: Hours per week | B17: =B16/B7 -> 5.4230769
A18: FTE needed (measured) | B18: =B17/B8 -> 0.13557692
A19: Claim ÷ measured | B19: =B5/B17 -> 7.3758865 | C19: How far the felt load exceeds the logged load
A21: Unit cost
A22: Loaded cost per FTE per quarter | B22: =B9/B10 -> 10400
A23: Loaded cost per FTE per year | B23: =B22*4 -> 41600
A24: Loaded cost per hour | B24: =B23/(52*B8) -> 20
A26: The number
A27: Support hire avoided, per year | B27: =(B6-B11)*B23 -> 41600 | C27: Formula: (FTE requested − incremental FTE needed) × loaded cost per FTE per year
A28: Confidence | B28: Medium | C28: High on Q1 (every row measured). Open on Q2 volume — see 'Stress tests' rows 18–23.
A30: Bounds (worst case: Ops' '#47 this week' is typical for Q2)
A31: Worst case — FTE needed, manual | B31: ='Stress tests'!B21 -> 0.51613248
A32: Worst case — value per year, manual | B32: =MAX(0,B6-B31)*B23 -> 20128.889 | C32: Half a person still avoided
A33: Worst case — FTE needed, IF thumbnail swaps were also automated (not selected) | B33: ='Stress tests'!B23 -> 0.25502137 | C33: Scenario only. The selected automation is tax forms (D1), which doesn't touch thumbnails; the headline floor is B32.
A34: Worst case — value per year, IF thumbnails automated (not selected) | B34: =MAX(0,B6-B33)*B23 -> 30991.111
A36: ="Answer: "&TEXT(B27,"$#,##0")&" per year — support hire avoided. Measured load "&TEXT(B17,"0.0")&" h/week ("&TEXT(B18,"0.00")&" FTE) vs "&B5&" h/week claimed. Range "&TEXT(B32,"$#,##0")&" – "&TEXT(B27,"$#,##0")&"." -> Answer: $41,600 per year — support hire avoided. Measured load 5.4 h/week (0.14 FTE) vs 40 h/week claimed. Range $20,129 – $41,600.
A38: Unblocker: Q2 support tickets (same columns, Apr 1 – Jun 30). Paste below row 142 on 'Tickets (raw)' and extend ranges, or rerun the builder.

Sheet Stress tests
A1: Where a finance person will push — each test recomputed live
A3: Under-logging: tickets miss some effort
A4: FTE needed if real effort = 2× logged | B4: =Summary!B17*2/Summary!B8 -> 0.27115385 | C4: Still < 0.5 FTE → holds
A5: FTE needed if real effort = 3× logged | B5: =Summary!B17*3/Summary!B8 -> 0.40673077 | C5: Still < 0.5 FTE → holds
A6: Share of effort tickets must capture for the 40 h claim to be true | B6: =Summary!B17/Summary!B5 -> 0.13557692 | C6: Implausibly low without evidence of large off-ticket work
A8: Seasonality and growth
A9: Tax-form share of Q1 minutes (W-9/W-8 season) | B9: =Breakdown!E4 -> 0.36761229 | C9: NOT a proven peak: tax forms come with new-creator onboarding (slack L171) and Ops calls June 'tax form season again' (L201). Treat as neutral.
A10: Hours, 2026-01 | B10: =Breakdown!D14 -> 24.083333
A11: Hours, 2026-03 | B11: =Breakdown!D16 -> 24.666667
A12: Change first → last month | B12: =B11/B10-1 -> 0.024221453 | C12: Flat to slightly up
A13: FTE needed at 2× ticket volume | B13: =Summary!B18*2 -> 0.27115385 | C13: Holds
A15: The '#47 this week' challenge (slack_export.md L193, May 21)
A16: Thumbnail requests in one week (Ops claim) | B16: =Sources!$D$9 -> 47 | C16: Sources row — verbatim quote there
A17: Q1 average thumbnail tickets per week | B17: =Breakdown!B5/Summary!B7 -> 4.8461538
A18: Q1 busiest week (thumbnail tickets) | B18: =Breakdown!$B$34 -> 6 | C18: 47 would be this many times the busiest Q1 week → | D18: =B16/B18 -> 7.8333333
A19: Average minutes per thumbnail ticket | B19: =Breakdown!F5 -> 21.666667
A20: Other categories, h/week (Q1 rate) | B20: =(Summary!B15-Breakdown!C5)/60/Summary!B7 -> 3.6730769
A21: Worst case — FTE needed, manual | B21: =(B16*B19/60+B20)/Summary!B8 -> 0.51613248 | C21: If every week in Q2 were like May 21
A22: Automation fallback rate (assumption) | B22: 0.2 | C22: Analysis/automation/playbooks.json — share of deflected tickets still needing a person
A23: Worst case — FTE needed, IF thumbnails automated (not selected) | B23: =(B16*((1-B22)*B24+B22*B19)/60+B20)/Summary!B8 -> 0.25502137 | C23: Thumbnails deflected to self-serve; other work unchanged
A24: Residual minutes per automated thumbnail (assumption) | B24: 5 | C24: playbooks.json — human spot-check time
A26: Verdict: the number survives every test except a Q2 surge at the '#47' rate without automation — then about half a person is needed and the value falls to the 'manual' bound on the Summary.

Sheet Tickets (raw)
A1: Raw export: support_tickets_q1_2026.csv — all 140 rows as delivered. Month and ISO week are formulas; Flag/Comment are mine.
A2: Source line | B2: Ticket_ID | C2: Date | D2: Category | E2: Submitted_By | F2: Assigned_To | G2: Handle_Minutes | H2: Status | I2: Month | J2: ISO week | K2: Flag | L2: Comment
A3: 2 | B3: TCK-1001 | C3: 46024 | D3: Thumbnail re-upload | E3: creator_avaloncreates | F3: Ops Support | G3: 25 | H3: Closed | I3: =TEXT(C3,"yyyy-mm") -> 2026-01 | J3: =WEEKNUM(C3,21) -> 1
A4: 3 | B4: TCK-1002 | C4: 46024 | D4: Tax form (W-9/W-8) | E4: creator_brightpixel | F4: Ops Support | G4: 50 | H4: Closed | I4: =TEXT(C4,"yyyy-mm") -> 2026-01 | J4: =WEEKNUM(C4,21) -> 1
A5: 4 | B5: TCK-1003 | C5: 46025 | D5: Login issue | E5: creator_chartedwaters | F5: Ops Support | G5: 15 | H5: Closed | I5: =TEXT(C5,"yyyy-mm") -> 2026-01 | J5: =WEEKNUM(C5,21) -> 1
A6: 5 | B6: TCK-1004 | C6: 46025 | D6: Thumbnail re-upload | E6: creator_dunemotion | F6: Ops Support | G6: 20 | H6: Closed | I6: =TEXT(C6,"yyyy-mm") -> 2026-01 | J6: =WEEKNUM(C6,21) -> 1
A7: 6 | B7: TCK-1005 | C7: 46027 | D7: Payout question | E7: creator_emberlite | F7: Ops Support | G7: 55 | H7: Closed | I7: =TEXT(C7,"yyyy-mm") -> 2026-01 | J7: =WEEKNUM(C7,21) -> 2
A8: 7 | B8: TCK-1006 | C8: 46027 | D8: Tax form (W-9/W-8) | E8: creator_foxglovestudio | F8: Ops Support | G8: 45 | H8: Closed | I8: =TEXT(C8,"yyyy-mm") -> 2026-01 | J8: =WEEKNUM(C8,21) -> 2
A9: 8 | B9: TCK-1007 | C9: 46028 | D9: Thumbnail re-upload | E9: creator_glasscanyon | F9: Ops Support | G9: 25 | H9: Closed | I9: =TEXT(C9,"yyyy-mm") -> 2026-01 | J9: =WEEKNUM(C9,21) -> 2
A10: 9 | B10: TCK-1008 | C10: 46028 | D10: Thumbnail re-upload | E10: creator_harborlight | F10: Ops Support | G10: 20 | H10: Closed | I10: =TEXT(C10,"yyyy-mm") -> 2026-01 | J10: =WEEKNUM(C10,21) -> 2
A11: 10 | B11: TCK-1009 | C11: 46029 | D11: Tax form (W-9/W-8) | E11: creator_ivoryreef | F11: Ops Support | G11: 45 | H11: Closed | I11: =TEXT(C11,"yyyy-mm") -> 2026-01 | J11: =WEEKNUM(C11,21) -> 2
A12: 11 | B12: TCK-1010 | C12: 46029 | D12: Login issue | E12: creator_junipertrail | F12: Ops Support | G12: 10 | H12: Closed | I12: =TEXT(C12,"yyyy-mm") -> 2026-01 | J12: =WEEKNUM(C12,21) -> 2
A13: 12 | B13: TCK-1011 | C13: 46030 | D13: Thumbnail re-upload | E13: creator_kelpforest | F13: Ops Support | G13: 25 | H13: Closed | I13: =TEXT(C13,"yyyy-mm") -> 2026-01 | J13: =WEEKNUM(C13,21) -> 2
A14: 13 | B14: TCK-1012 | C14: 46030 | D14: Payout question | E14: creator_lanternbay | F14: Ops Support | G14: 50 | H14: Closed | I14: =TEXT(C14,"yyyy-mm") -> 2026-01 | J14: =WEEKNUM(C14,21) -> 2
A15: 14 | B15: TCK-1013 | C15: 46031 | D15: Tax form (W-9/W-8) | E15: creator_moonlitpath | G15: 45 | H15: Closed | I15: =TEXT(C15,"yyyy-mm") -> 2026-01 | J15: =WEEKNUM(C15,21) -> 2 | K15: DATA QUALITY | L15: Assigned_To blank. Kept: effort is still logged in Handle_Minutes.
A16: 15 | B16: TCK-1014 | C16: 46031 | D16: Thumbnail re-upload | E16: creator_northstarvideo | F16: Ops Support | G16: 20 | H16: Closed | I16: =TEXT(C16,"yyyy-mm") -> 2026-01 | J16: =WEEKNUM(C16,21) -> 2
A17: 16 | B17: TCK-1015 | C17: 46034 | D17: Thumbnail re-upload | E17: creator_oakhollow | F17: Ops Support | G17: 25 | H17: Closed | I17: =TEXT(C17,"yyyy-mm") -> 2026-01 | J17: =WEEKNUM(C17,21) -> 3
A18: 17 | B18: TCK-1016 | C18: 46034 | D18: Account access | E18: creator_pinegrove | F18: Ops Support | G18: 25 | H18: Closed | I18: =TEXT(C18,"yyyy-mm") -> 2026-01 | J18: =WEEKNUM(C18,21) -> 3
A19: 18 | B19: TCK-1017 | C19: 46035 | D19: Tax form (W-9/W-8) | E19: creator_quietharbor | F19: Ops Support | G19: 40 | H19: Closed | I19: =TEXT(C19,"yyyy-mm") -> 2026-01 | J19: =WEEKNUM(C19,21) -> 3
A20: 19 | B20: TCK-1018 | C20: 46035 | D20: Thumbnail re-upload | E20: creator_riverstone | F20: Ops Support | G20: 20 | H20: Closed | I20: =TEXT(C20,"yyyy-mm") -> 2026-01 | J20: =WEEKNUM(C20,21) -> 3
A21: 20 | B21: TCK-1019 | C21: 46036 | D21: Payout question | E21: creator_silvercrest | F21: Ops Support | G21: 45 | H21: Closed | I21: =TEXT(C21,"yyyy-mm") -> 2026-01 | J21: =WEEKNUM(C21,21) -> 3
A22: 21 | B22: TCK-1020 | C22: 46036 | D22: Thumbnail re-upload | E22: creator_tidalwave | F22: Ops Support | G22: 25 | H22: Closed | I22: =TEXT(C22,"yyyy-mm") -> 2026-01 | J22: =WEEKNUM(C22,21) -> 3
A23: 22 | B23: TCK-1021 | C23: 46037 | D23: Tax form (W-9/W-8) | E23: creator_umberglow | F23: Ops Support | G23: 50 | H23: Closed | I23: =TEXT(C23,"yyyy-mm") -> 2026-01 | J23: =WEEKNUM(C23,21) -> 3
A24: 23 | B24: TCK-1022 | C24: 46037 | D24: Login issue | E24: creator_violetdusk | F24: Ops Support | G24: 10 | H24: Closed | I24: =TEXT(C24,"yyyy-mm") -> 2026-01 | J24: =WEEKNUM(C24,21) -> 3
A25: 24 | B25: TCK-1023 | C25: 46038 | D25: Thumbnail re-upload | E25: creator_wildfern | F25: Ops Support | G25: 20 | H25: Closed | I25: =TEXT(C25,"yyyy-mm") -> 2026-01 | J25: =WEEKNUM(C25,21) -> 3
A26: 25 | B26: TCK-1024 | C26: 46038 | D26: Thumbnail re-upload | E26: creator_xanaduclips | F26: Ops Support | G26: 25 | H26: Closed | I26: =TEXT(C26,"yyyy-mm") -> 2026-01 | J26: =WEEKNUM(C26,21) -> 3
A27: 26 | B27: TCK-1025 | C27: 46041 | D27: Tax form (W-9/W-8) | E27: creator_yellowpine | F27: Ops Support | G27: 45 | H27: Closed | I27: =TEXT(C27,"yyyy-mm") -> 2026-01 | J27: =WEEKNUM(C27,21) -> 4
... A39: 38 | B39: TCK-1037 | C39: 46049 | D39: Tax form (W-9/W-8) | E39: creator_larkspur | F39: Ops Support | G39: 45 | H39: Closed | I39: =TEXT(C39,"yyyy-mm") -> 2026-01 | J39: =WEEKNUM(C39,21) -> 5
A40: 39 | B40: TCK-1038 | C40: 46049 | D40: Thumbnail re-upload | E40: creator_mistralwind | G40: 25 | H40: Closed | I40: =TEXT(C40,"yyyy-mm") -> 2026-01 | J40: =WEEKNUM(C40,21) -> 5 | K40: DATA QUALITY | L40: Assigned_To blank. Kept: effort is still logged in Handle_Minutes.
A41: 40 | B41: TCK-1039 | C41: 46050 | D41: Account access | E41: creator_nightowl | F41: Ops Support | G41: 20 | H41: Closed | I41: =TEXT(C41,"yyyy-mm") -> 2026-01 | J41: =WEEKNUM(C41,21) -> 5
A42: 41 | B42: TCK-1040 | C42: 46050 | D42: Thumbnail re-upload | E42: creator_opalbeach | F42: Ops Support | G42: 25 | H42: Closed | I42: =TEXT(C42,"yyyy-mm") -> 2026-01 | J42: =WEEKNUM(C42,21) -> 5
A43: 42 | B43: TCK-1041 | C43: 46051 | D43: Tax form (W-9/W-8) | E43: creator_pebblecreek | F43: Ops Support | G43: 40 | H43: Closed | I43: =TEXT(C43,"yyyy-mm") -> 2026-01 | J43: =WEEKNUM(C43,21) -> 5
A44: 43 | B44: TCK-1042 | C44: 46051 | D44: Thumbnail re-upload | E44: creator_quillfeather | F44: Ops Support | G44: 20 | H44: Closed | I44: =TEXT(C44,"yyyy-mm") -> 2026-01 | J44: =WEEKNUM(C44,21) -> 5
A45: 44 | B45: TCK-1043 | C45: 46052 | D45: Payout question | E45: creator_redwoodway | F45: Ops Support | G45: 50 | H45: Closed | I45: =TEXT(C45,"yyyy-mm") -> 2026-01 | J45: =WEEKNUM(C45,21) -> 5
A46: 45 | B46: TCK-1044 | C46: 46052 | D46: Thumbnail re-upload | E46: creator_sanddollar | F46: Ops Support | G46: 25 | H46: Closed | I46: =TEXT(C46,"yyyy-mm") -> 2026-01 | J46: =WEEKNUM(C46,21) -> 5
A47: 46 | B47: TCK-1045 | C47: 46055 | D47: Tax form (W-9/W-8) | E47: creator_thornbush | F47: Ops Support | G47: 45 | H47: Closed | I47: =TEXT(C47,"yyyy-mm") -> 2026-02 | J47: =WEEKNUM(C47,21) -> 6
A48: 47 | B48: TCK-1046 | C48: 46055 | D48: Thumbnail re-upload | E48: creator_underbrush | F48: Ops Support | G48: 20 | H48: Closed | I48: =TEXT(C48,"yyyy-mm") -> 2026-02 | J48: =WEEKNUM(C48,21) -> 6
A49: 48 | B49: TCK-1047 | C49: 46056 | D49: Login issue | E49: creator_vellichor | F49: Ops Support | G49: 10 | H49: Closed | I49: =TEXT(C49,"yyyy-mm") -> 2026-02 | J49: =WEEKNUM(C49,21) -> 6
A50: 49 | B50: TCK-1048 | C50: 46056 | D50: Thumbnail re-upload | E50: creator_windrose | F50: Ops Support | G50: 25 | H50: Closed | I50: =TEXT(C50,"yyyy-mm") -> 2026-02 | J50: =WEEKNUM(C50,21) -> 6
A51: 50 | B51: TCK-1049 | C51: 46057 | D51: Tax form (W-9/W-8) | E51: creator_xeriscape | F51: Ops Support | G51: 50 | H51: Closed | I51: =TEXT(C51,"yyyy-mm") -> 2026-02 | J51: =WEEKNUM(C51,21) -> 6
A52: 51 | B52: TCK-1050 | C52: 46057 | D52: Payout question | E52: creator_yarrowmeadow | F52: Ops Support | G52: 55 | H52: Closed | I52: =TEXT(C52,"yyyy-mm") -> 2026-02 | J52: =WEEKNUM(C52,21) -> 6
... A69: 68 | B69: TCK-1067 | C69: 46070 | D69: Payout question | E69: creator_pondscum | F69: Ops Support | G69: 55 | H69: Closed | I69: =TEXT(C69,"yyyy-mm") -> 2026-02 | J69: =WEEKNUM(C69,21) -> 8
A70: 69 | B70: TCK-1068 | C70: 46070 | D70: Thumbnail re-upload | E70: creator_quartzridge | G70: 20 | H70: Closed | I70: =TEXT(C70,"yyyy-mm") -> 2026-02 | J70: =WEEKNUM(C70,21) -> 8 | K70: DATA QUALITY | L70: Assigned_To blank. Kept: effort is still logged in Handle_Minutes.
A71: 70 | B71: TCK-1069 | C71: 46071 | D71: Tax form (W-9/W-8) | E71: creator_rushreed | F71: Ops Support | G71: 45 | H71: Closed | I71: =TEXT(C71,"yyyy-mm") -> 2026-02 | J71: =WEEKNUM(C71,21) -> 8
A72: 71 | B72: TCK-1070 | C72: 46071 | D72: Login issue | E72: creator_seafoam | F72: Ops Support | G72: 10 | H72: Closed | I72: =TEXT(C72,"yyyy-mm") -> 2026-02 | J72: =WEEKNUM(C72,21) -> 8
A73: 72 | B73: TCK-1071 | C73: 46072 | D73: Thumbnail re-upload | E73: creator_tumbleweed | F73: Ops Support | G73: 20 | H73: Closed | I73: =TEXT(C73,"yyyy-mm") -> 2026-02 | J73: =WEEKNUM(C73,21) -> 8
A74: 73 | B74: TCK-1072 | C74: 46072 | D74: Thumbnail re-upload | E74: creator_underpass | F74: Ops Support | G74: 25 | H74: Closed | I74: =TEXT(C74,"yyyy-mm") -> 2026-02 | J74: =WEEKNUM(C74,21) -> 8
A75: 74 | B75: TCK-1073 | C75: 46073 | D75: Tax form (W-9/W-8) | E75: creator_vinetrellis | F75: Ops Support | G75: 45 | H75: Closed | I75: =TEXT(C75,"yyyy-mm") -> 2026-02 | J75: =WEEKNUM(C75,21) -> 8
A76: 75 | B76: TCK-1074 | C76: 46073 | D76: Payout question | E76: creator_willowbend | F76: Ops Support | G76: 50 | H76: Closed | I76: =TEXT(C76,"yyyy-mm") -> 2026-02 | J76: =WEEKNUM(C76,21) -> 8
A77: 76 | B77: TCK-1075 | C77: 46076 | D77: Thumbnail re-upload | E77: creator_xylophone | F77: Ops Support | G77: 20 | H77: Closed | I77: =TEXT(C77,"yyyy-mm") -> 2026-02 | J77: =WEEKNUM(C77,21) -> 9
A78: 77 | B78: TCK-1076 | C78: 46076 | D78: Thumbnail re-upload | E78: creator_yewberry | F78: Ops Support | G78: 25 | H78: Closed | I78: =TEXT(C78,"yyyy-mm") -> 2026-02 | J78: =WEEKNUM(C78,21) -> 9
A79: 78 | B79: TCK-1077 | C79: 46077 | D79: Tax form (W-9/W-8) | E79: creator_zephyrhill | F79: Ops Support | G79: 45 | H79: Closed | I79: =TEXT(C79,"yyyy-mm") -> 2026-02 | J79: =WEEKNUM(C79,21) -> 9
A80: 79 | B80: TCK-1078 | C80: 46077 | D80: Account access | E80: creator_alderwood | F80: Ops Support | G80: 25 | H80: Closed | I80: =TEXT(C80,"yyyy-mm") -> 2026-02 | J80: =WEEKNUM(C80,21) -> 9
A81: 80 | B81: TCK-1079 | C81: 46078 | D81: Thumbnail re-upload | E81: creator_bramblerose | F81: Ops Support | G81: 20 | H81: Closed | I81: =TEXT(C81,"yyyy-mm") -> 2026-02 | J81: =WEEKNUM(C81,21) -> 9
A82: 81 | B82: TCK-1080 | C82: 46078 | D82: Login issue | E82: creator_cloudbank | F82: Ops Support | G82: 10 | H82: Closed | I82: =TEXT(C82,"yyyy-mm") -> 2026-02 | J82: =WEEKNUM(C82,21) -> 9
... A101: 100 | B101: TCK-1099 | C101: 46092 | D101: Payout question | E101: creator_verdantglen | F101: Ops Support | G101: 50 | H101: Closed | I101: =TEXT(C101,"yyyy-mm") -> 2026-03 | J101: =WEEKNUM(C101,21) -> 11
A102: 101 | B102: TCK-1100 | C102: 46092 | D102: Thumbnail re-upload | E102: creator_waxwing | G102: 20 | H102: Closed | I102: =TEXT(C102,"yyyy-mm") -> 2026-03 | J102: =WEEKNUM(C102,21) -> 11 | K102: DATA QUALITY | L102: Assigned_To blank. Kept: effort is still logged in Handle_Minutes.
A103: 102 | B103: TCK-1101 | C103: 46093 | D103: Tax form (W-9/W-8) | E103: creator_xanthegold | F103: Ops Support | G103: 45 | H103: Closed | I103: =TEXT(C103,"yyyy-mm") -> 2026-03 | J103: =WEEKNUM(C103,21) -> 11
A104: 103 | B104: TCK-1102 | C104: 46093 | D104: Thumbnail re-upload | E104: creator_yonderfield | F104: Ops Support | G104: 25 | H104: Closed | I104: =TEXT(C104,"yyyy-mm") -> 2026-03 | J104: =WEEKNUM(C104,21) -> 11
A105: 104 | B105: TCK-1103 | C105: 46094 | D105: Account access | E105: creator_zealouspeak | F105: Ops Support | G105: 25 | H105: Closed | I105: =TEXT(C105,"yyyy-mm") -> 2026-03 | J105: =WEEKNUM(C105,21) -> 11
A106: 105 | B106: TCK-1104 | C106: 46094 | D106: Thumbnail re-upload | E106: creator_arborvale | F106: Ops Support | G106: 20 | H106: Closed | I106: =TEXT(C106,"yyyy-mm") -> 2026-03 | J106: =WEEKNUM(C106,21) -> 11
A107: 106 | B107: TCK-1105 | C107: 46097 | D107: Tax form (W-9/W-8) | E107: creator_bayberry | F107: Ops Support | G107: 50 | H107: Closed | I107: =TEXT(C107,"yyyy-mm") -> 2026-03 | J107: =WEEKNUM(C107,21) -> 12
A108: 107 | B108: TCK-1106 | C108: 46097 | D108: Thumbnail re-upload | E108: creator_cinderpath | F108: Ops Support | G108: 25 | H108: Closed | I108: =TEXT(C108,"yyyy-mm") -> 2026-03 | J108: =WEEKNUM(C108,21) -> 12
A109: 108 | B109: TCK-1107 | C109: 46098 | D109: Payout question | E109: creator_driftshore | F109: Ops Support | G109: 55 | H109: Closed | I109: =TEXT(C109,"yyyy-mm") -> 2026-03 | J109: =WEEKNUM(C109,21) -> 12
A110: 109 | B110: TCK-1108 | C110: 46098 | D110: Thumbnail re-upload | E110: creator_elderflower | F110: Ops Support | G110: 20 | H110: Closed | I110: =TEXT(C110,"yyyy-mm") -> 2026-03 | J110: =WEEKNUM(C110,21) -> 12
A111: 110 | B111: TCK-1109 | C111: 46099 | D111: Tax form (W-9/W-8) | E111: creator_foampeak | F111: Ops Support | G111: 45 | H111: Closed | I111: =TEXT(C111,"yyyy-mm") -> 2026-03 | J111: =WEEKNUM(C111,21) -> 12
A112: 111 | B112: TCK-1110 | C112: 46099 | D112: Login issue | E112: creator_grottoblue | F112: Ops Support | G112: 10 | H112: Closed | I112: =TEXT(C112,"yyyy-mm") -> 2026-03 | J112: =WEEKNUM(C112,21) -> 12
A113: 112 | B113: TCK-1111 | C113: 46100 | D113: Thumbnail re-upload | E113: creator_hillcrest | F113: Ops Support | G113: 20 | H113: Closed | I113: =TEXT(C113,"yyyy-mm") -> 2026-03 | J113: =WEEKNUM(C113,21) -> 12
A114: 113 | B114: TCK-1112 | C114: 46100 | D114: Thumbnail re-upload | E114: creator_inletcove | F114: Ops Support | G114: 25 | H114: Closed | I114: =TEXT(C114,"yyyy-mm") -> 2026-03 | J114: =WEEKNUM(C114,21) -> 12
... A128: 127 | B128: TCK-1126 | C128: 46111 | D128: Thumbnail re-upload | E128: creator_wrenfield | F128: Ops Support | G128: 15 | H128: Closed | I128: =TEXT(C128,"yyyy-mm") -> 2026-03 | J128: =WEEKNUM(C128,21) -> 14
A129: 128 | B129: TCK-1127 | C129: 46111 | D129: Thumbnail re-upload | E129: creator_yarrowhill | F129: Ops Support | G129: 20 | H129: Open | I129: =TEXT(C129,"yyyy-mm") -> 2026-03 | J129: =WEEKNUM(C129,21) -> 14 | K129: OPEN | L129: Still open at quarter end; minutes may grow. Kept as logged.
A130: 129 | B130: TCK-1128 | C130: 46112 | D130: Tax form (W-9/W-8) | E130: creator_zinniadell | F130: Ops Support | G130: 30 | H130: Open | I130: =TEXT(C130,"yyyy-mm") -> 2026-03 | J130: =WEEKNUM(C130,21) -> 14 | K130: OPEN | L130: Still open at quarter end; minutes may grow. Kept as logged.
A131: 130 | B131: TCK-1129 | C131: 46112 | D131: Payout question | E131: creator_ashenmoor | F131: Ops Support | G131: 35 | H131: Closed | I131: =TEXT(C131,"yyyy-mm") -> 2026-03 | J131: =WEEKNUM(C131,21) -> 14
A132: 131 | B132: TCK-1130 | C132: 46112 | D132: Thumbnail re-upload | E132: creator_blueheron | F132: Ops Support | G132: 15 | H132: Closed | I132: =TEXT(C132,"yyyy-mm") -> 2026-03 | J132: =WEEKNUM(C132,21) -> 14
A133: 132 | B133: TCK-1131 | C133: 46032 | D133: Thumbnail re-upload | E133: creator_cliffside | F133: Ops Support | G133: 20 | H133: Closed | I133: =TEXT(C133,"yyyy-mm") -> 2026-01 | J133: =WEEKNUM(C133,21) -> 2 | K133: BACK-FILLED | L133: Dated 2026-01-10 but appended after the 2026-03-31 tickets — one of 10 rows (TCK-1131–1140, 235 min) added late. Not a duplicate: no earlier ticket from this creator. Kept.
A134: 133 | B134: TCK-1132 | C134: 46045 | D134: Tax form (W-9/W-8) | E134: creator_dewpoint | F134: Ops Support | G134: 30 | H134: Closed | I134: =TEXT(C134,"yyyy-mm") -> 2026-01 | J134: =WEEKNUM(C134,21) -> 4 | K134: BACK-FILLED | L134: Dated 2026-01-23 but appended after the 2026-03-31 tickets — one of 10 rows (TCK-1131–1140, 235 min) added late. Not a duplicate: no earlier ticket from this creator. Kept.
A135: 134 | B135: TCK-1133 | C135: 46060 | D135: Login issue | E135: creator_eaglecrest | F135: Ops Support | G135: 10 | H135: Closed | I135: =TEXT(C135,"yyyy-mm") -> 2026-02 | J135: =WEEKNUM(C135,21) -> 6 | K135: BACK-FILLED | L135: Dated 2026-02-07 but appended after the 2026-03-31 tickets — one of 10 rows (TCK-1131–1140, 235 min) added late. Not a duplicate: no earlier ticket from this creator. Kept.
A136: 135 | B136: TCK-1134 | C136: 46073 | D136: Thumbnail re-upload | E136: creator_fogbank | F136: Ops Support | G136: 15 | H136: Closed | I136: =TEXT(C136,"yyyy-mm") -> 2026-02 | J136: =WEEKNUM(C136,21) -> 8 | K136: BACK-FILLED | L136: Dated 2026-02-20 but appended after the 2026-03-31 tickets — one of 10 rows (TCK-1131–1140, 235 min) added late. Not a duplicate: no earlier ticket from this creator. Kept.
A137: 136 | B137: TCK-1135 | C137: 46087 | D137: Payout question | E137: creator_glacierway | F137: Ops Support | G137: 40 | H137: Closed | I137: =TEXT(C137,"yyyy-mm") -> 2026-03 | J137: =WEEKNUM(C137,21) -> 10 | K137: BACK-FILLED | L137: Dated 2026-03-06 but appended after the 2026-03-31 tickets — one of 10 rows (TCK-1131–1140, 235 min) added late. Not a duplicate: no earlier ticket from this creator. Kept.
A138: 137 | B138: TCK-1136 | C138: 46094 | D138: Tax form (W-9/W-8) | E138: creator_havenport | F138: Ops Support | G138: 30 | H138: Closed | I138: =TEXT(C138,"yyyy-mm") -> 2026-03 | J138: =WEEKNUM(C138,21) -> 11 | K138: BACK-FILLED | L138: Dated 2026-03-13 but appended after the 2026-03-31 tickets — one of 10 rows (TCK-1131–1140, 235 min) added late. Not a duplicate: no earlier ticket from this creator. Kept.
A139: 138 | B139: TCK-1137 | C139: 46039 | D139: Thumbnail re-upload | E139: creator_inglewood | F139: Ops Support | G139: 20 | H139: Closed | I139: =TEXT(C139,"yyyy-mm") -> 2026-01 | J139: =WEEKNUM(C139,21) -> 3 | K139: BACK-FILLED | L139: Dated 2026-01-17 but appended after the 2026-03-31 tickets — one of 10 rows (TCK-1131–1140, 235 min) added late. Not a duplicate: no earlier ticket from this creator. Kept.
A140: 139 | B140: TCK-1138 | C140: 46067 | D140: Thumbnail re-upload | E140: creator_jackpine | F140: Ops Support | G140: 15 | H140: Closed | I140: =TEXT(C140,"yyyy-mm") -> 2026-02 | J140: =WEEKNUM(C140,21) -> 7 | K140: BACK-FILLED | L140: Dated 2026-02-14 but appended after the 2026-03-31 tickets — one of 10 rows (TCK-1131–1140, 235 min) added late. Not a duplicate: no earlier ticket from this creator. Kept.
A141: 140 | B141: TCK-1139 | C141: 46085 | D141: Account access | E141: creator_kindling | F141: Ops Support | G141: 25 | H141: Closed | I141: =TEXT(C141,"yyyy-mm") -> 2026-03 | J141: =WEEKNUM(C141,21) -> 10 | K141: BACK-FILLED | L141: Dated 2026-03-04 but appended after the 2026-03-31 tickets — one of 10 rows (TCK-1131–1140, 235 min) added late. Not a duplicate: no earlier ticket from this creator. Kept.
A142: 141 | B142: TCK-1140 | C142: 46102 | D142: Tax form (W-9/W-8) | E142: creator_lavendermist | F142: Ops Support | G142: 30 | H142: Closed | I142: =TEXT(C142,"yyyy-mm") -> 2026-03 | J142: =WEEKNUM(C142,21) -> 12 | K142: BACK-FILLED | L142: Dated 2026-03-21 but appended after the 2026-03-31 tickets — one of 10 rows (TCK-1131–1140, 235 min) added late. Not a duplicate: no earlier ticket from this creator. Kept.

Sheet Breakdown
A1: Ticket totals by category, month and ISO week — all COUNTIFS/SUMIFS on 'Tickets (raw)'.
A3: Category | B3: Tickets | C3: Minutes | D3: Hours | E3: Share of time | F3: Avg min/ticket
A4: Tax form (W-9/W-8) | B4: =COUNTIFS('Tickets (raw)'!$D$3:$D$142,A4) -> 36 | C4: =SUMIFS('Tickets (raw)'!$G$3:$G$142,'Tickets (raw)'!$D$3:$D$142,A4) -> 1555 | D4: =C4/60 -> 25.916667 | E4: =C4/$C$10 -> 0.36761229 | F4: =C4/B4 -> 43.194444
A5: Thumbnail re-upload | B5: =COUNTIFS('Tickets (raw)'!$D$3:$D$142,A5) -> 63 | C5: =SUMIFS('Tickets (raw)'!$G$3:$G$142,'Tickets (raw)'!$D$3:$D$142,A5) -> 1365 | D5: =C5/60 -> 22.75 | E5: =C5/$C$10 -> 0.32269504 | F5: =C5/B5 -> 21.666667
A6: Payout question | B6: =COUNTIFS('Tickets (raw)'!$D$3:$D$142,A6) -> 18 | C6: =SUMIFS('Tickets (raw)'!$G$3:$G$142,'Tickets (raw)'!$D$3:$D$142,A6) -> 875 | D6: =C6/60 -> 14.583333 | E6: =C6/$C$10 -> 0.20685579 | F6: =C6/B6 -> 48.611111
A7: Account access | B7: =COUNTIFS('Tickets (raw)'!$D$3:$D$142,A7) -> 7 | C7: =SUMIFS('Tickets (raw)'!$G$3:$G$142,'Tickets (raw)'!$D$3:$D$142,A7) -> 170 | D7: =C7/60 -> 2.8333333 | E7: =C7/$C$10 -> 0.040189125 | F7: =C7/B7 -> 24.285714
A8: Login issue | B8: =COUNTIFS('Tickets (raw)'!$D$3:$D$142,A8) -> 13 | C8: =SUMIFS('Tickets (raw)'!$G$3:$G$142,'Tickets (raw)'!$D$3:$D$142,A8) -> 135 | D8: =C8/60 -> 2.25 | E8: =C8/$C$10 -> 0.031914894 | F8: =C8/B8 -> 10.384615
A9: Content takedown | B9: =COUNTIFS('Tickets (raw)'!$D$3:$D$142,A9) -> 3 | C9: =SUMIFS('Tickets (raw)'!$G$3:$G$142,'Tickets (raw)'!$D$3:$D$142,A9) -> 130 | D9: =C9/60 -> 2.1666667 | E9: =C9/$C$10 -> 0.030732861 | F9: =C9/B9 -> 43.333333
A10: Total | B10: =SUM(B4:B9) -> 140 | C10: =SUM(C4:C9) -> 4230 | D10: =C10/60 -> 70.5 | E10: =C10/C10 -> 1
A13: Month | B13: Tickets | C13: Minutes | D13: Hours
A14: 2026-01 | B14: =COUNTIFS('Tickets (raw)'!$I$3:$I$142,A14) -> 47 | C14: =SUMIFS('Tickets (raw)'!$G$3:$G$142,'Tickets (raw)'!$I$3:$I$142,A14) -> 1445 | D14: =C14/60 -> 24.083333
A15: 2026-02 | B15: =COUNTIFS('Tickets (raw)'!$I$3:$I$142,A15) -> 43 | C15: =SUMIFS('Tickets (raw)'!$G$3:$G$142,'Tickets (raw)'!$I$3:$I$142,A15) -> 1305 | D15: =C15/60 -> 21.75
A16: 2026-03 | B16: =COUNTIFS('Tickets (raw)'!$I$3:$I$142,A16) -> 50 | C16: =SUMIFS('Tickets (raw)'!$G$3:$G$142,'Tickets (raw)'!$I$3:$I$142,A16) -> 1480 | D16: =C16/60 -> 24.666667
A19: ISO week | B19: Thumbnail tickets
A20: 1 | B20: =COUNTIFS('Tickets (raw)'!$J$3:$J$142,A20,'Tickets (raw)'!$D$3:$D$142,"Thumbnail re-upload") -> 2
A21: 2 | B21: =COUNTIFS('Tickets (raw)'!$J$3:$J$142,A21,'Tickets (raw)'!$D$3:$D$142,"Thumbnail re-upload") -> 5
A22: 3 | B22: =COUNTIFS('Tickets (raw)'!$J$3:$J$142,A22,'Tickets (raw)'!$D$3:$D$142,"Thumbnail re-upload") -> 6
A23: 4 | B23: =COUNTIFS('Tickets (raw)'!$J$3:$J$142,A23,'Tickets (raw)'!$D$3:$D$142,"Thumbnail re-upload") -> 4
A24: 5 | B24: =COUNTIFS('Tickets (raw)'!$J$3:$J$142,A24,'Tickets (raw)'!$D$3:$D$142,"Thumbnail re-upload") -> 5
A25: 6 | B25: =COUNTIFS('Tickets (raw)'!$J$3:$J$142,A25,'Tickets (raw)'!$D$3:$D$142,"Thumbnail re-upload") -> 4
A26: 7 | B26: =COUNTIFS('Tickets (raw)'!$J$3:$J$142,A26,'Tickets (raw)'!$D$3:$D$142,"Thumbnail re-upload") -> 6
A27: 8 | B27: =COUNTIFS('Tickets (raw)'!$J$3:$J$142,A27,'Tickets (raw)'!$D$3:$D$142,"Thumbnail re-upload") -> 5
A28: 9 | B28: =COUNTIFS('Tickets (raw)'!$J$3:$J$142,A28,'Tickets (raw)'!$D$3:$D$142,"Thumbnail re-upload") -> 5
A29: 10 | B29: =COUNTIFS('Tickets (raw)'!$J$3:$J$142,A29,'Tickets (raw)'!$D$3:$D$142,"Thumbnail re-upload") -> 4
A30: 11 | B30: =COUNTIFS('Tickets (raw)'!$J$3:$J$142,A30,'Tickets (raw)'!$D$3:$D$142,"Thumbnail re-upload") -> 5
A31: 12 | B31: =COUNTIFS('Tickets (raw)'!$J$3:$J$142,A31,'Tickets (raw)'!$D$3:$D$142,"Thumbnail re-upload") -> 4
... A33: 14 | B33: =COUNTIFS('Tickets (raw)'!$J$3:$J$142,A33,'Tickets (raw)'!$D$3:$D$142,"Thumbnail re-upload") -> 3
A34: Busiest week | B34: =MAX(B20:B33) -> 6

Sheet Sources
A1: Every non-ticket input, quoted verbatim from its file and line. Column D holds the number the Summary uses.
A2: File | B2: Line | C2: Raw text (verbatim) | D2: Value used | E2: Used for
A3: pnl_q1_2026.csv | B3: 7 | C3: Personnel,Salaries & benefits (all teams),3120000,~300 FTE; loaded cost; see headcount_roster.csv | D3: 3120000 | E3: Loaded personnel cost, Q1
A4: headcount_roster.csv | B4: 18 | C4: TOTAL,300 | D4: 300 | E4: Headcount (FTE)
A5: slack_export.md | B5: 176 | C5: Honestly support is drowning. It's easily 40 hrs/week on creator support between the thumbnail swaps, the tax forms, and general "where's my payout" questions. We need help here. | D5: 40 | E5: Claimed support load, h/week (Liam, May 6)
A6: slack_export.md | B6: 188 | C6: Sure, pull it. But it FEELS like a full-time person's worth, minimum. | D6: 1 | E6: FTE requested ('a full-time person's worth')
A7: slack_export.md | B7: 179 | C7: 40 hrs/week is a lot — is that measured or a vibe? Before we ask for a hire I want the actual ticket data. | E7: People gates the hire on measured ticket data
A8: slack_export.md | B8: 185 | C8: We log support tickets — happy to pull the Q1 numbers if it helps right-size this. I suspect the felt-volume is higher than the measured volume, that's usually how it goes. | E8: Data offers ticket numbers; expects felt > measured
A9: slack_export.md | B9: 193 | C9: Thumbnail swap request #47 this week. I'm not exaggerating about the volume. If we automated self-serve thumbnail replacement half my tickets would vanish. | D9: 47 | E9: Thumbnail requests in one week, May 21 (stress test)
A10: slack_export.md | B10: 244 | C10: Q3 planning prep: if you want any new headcount considered, get it to me with justification by end of month. Note Sales is on freeze so don't bother submitting Sales reqs until that lifts. | E10: Decision timing: Q3 headcount asks due end of June
A11: Analysis/automation/playbooks.json | C11: fallback_rate / Thumbnail residual_minutes | E11: Automation assumptions (not bundle data) — see Stress tests

Sheet Cannot verify
A1: What I could NOT verify from the bundle — impact on the number and how to unblock.
A2: # | B2: Not verifiable | C2: Why it matters | D2: Direction if wrong | E2: Unblocker
A3: 1 | B3: Q2 ticket volume | C3: Only Q1 tickets exist; the 40 h claim and '#47' are from May. Searched folder, repo and all Slack/notes — none. | D3: Value falls toward the manual worst case | E3: Ben Okoro (Data) — Q2 export, same columns (slack L185)
A4: 2 | B4: A formal support req | C4: Roster open reqs (L21–L25) list none for Ops; the ask is only in Slack. | D4: Value is a decision avoided, not a budgeted cost | E4: Elena / Liam: was a req drafted for Q3?
A5: 3 | B5: Off-ticket effort | C5: Chasing by email/DM wouldn't be in Handle_Minutes. | D5: Load higher than logged (stress-tested 2×, 3×) | E5: Ops time study for 2 weeks
A6: 4 | B6: How Handle_Minutes is captured | C6: All 140 values are multiples of 5 (10–55) → likely estimates, not timers. | D6: Either direction | E6: Ask how the ticket tool records time
A7: 5 | B7: Role-specific loaded cost | C7: Only the company average exists ($3.12M ÷ 300). P&L says '~300 FTE', roster says 300. | D7: Dollar value moves; direction doesn't | E7: Finance: loaded cost for an ops coordinator
A8: 6 | B8: Why 10 tickets were back-filled | C8: TCK-1131–1140 (235 min, 5.6% of minutes) are dated Jan–Mar but appended after Mar 31. Distinct creators, so not duplicates. | D8: If more late entries exist, Q1 load grows slightly | E8: Ask Ops when/why these were logged
A9: 7 | B9: Non-creator support in the 40 h | C9: Ops may count work that isn't in the creator ticket log. | D9: Claim may be about a wider scope | E9: Ask Liam what the 40 h covers

Sheet Alternatives
A1: Value numbers considered and ranked lower — and why.
A2: Candidate | B2: Annual value | C2: Arithmetic | D2: Source | E2: Why ranked lower
A3: Support hire avoided (chosen) | B3: =Summary!B27 -> 41600 | C3: 1 FTE × loaded cost per FTE | D3: Summary | E3: Every input is a raw row; informs a live decision.
A4: Amplitude duplicate closed | B4: =7500*4 -> 30000 | C4: $7,500 per quarter × 4 | D4: pnl_q1_2026.csv L12–L13; slack L147–L153 | E4: Can't tell a cash leak from a booking error without the invoice.
A5: Brand-deal recon time saved | B5: =3*12*8*Summary!B24 -> 5760 | C5: 3 days × 12 months × 8 h × loaded $/h | D5: slack L108, L158; finance_review L11 | E5: Self-reported time; the 3 source exports aren't in the bundle.
A6: Support automation hours saved | B6: =29.9*4*Summary!B24 -> 2392 | C6: 29.9 h/qtr saved (modelled) × 4 × loaded $/h | D6: output/autopilot/report.md | E6: Modelled, and small. Its job is to keep the hire unnecessary.
